emotional_ai/__init__.py
emotional_ai/emotional_ai_lib.py
emotional_ai-0.1.0.dist-info/LICENSE
emotional_ai-0.1.0.dist-info/METADATA
emotional_ai-0.1.0.dist-info/WHEEL
emotional_ai-0.1.0.dist-info/top_level.txt
emotional_ai-0.1.0.dist-info/RECORD
