Metadata-Version: 2.2
Name: emotional_ai
Version: 0.1.0
Summary: Бібліотека емоційного ШІ
Home-page: https://github.com/andriy8800555355/emotional_ai
Author: Roflboy2009
Author-email: Andriy4521@ukr.net
Classifier: Programming Language :: Python :: 3
Classifier: License :: OSI Approved :: MIT License
Classifier: Operating System :: OS Independent
Requires-Python: >=3.6
License-File: LICENSE
Requires-Dist: matplotlib
Requires-Dist: openai
Requires-Dist: anthropic
Dynamic: author
Dynamic: author-email
Dynamic: classifier
Dynamic: description
Dynamic: description-content-type
Dynamic: home-page
Dynamic: requires-dist
Dynamic: requires-python
Dynamic: summary
